topovec/__init__.py
topovec/py.typed
topovec/core/__init__.py
topovec/core/colors.py
topovec/core/io.py
topovec/core/log.py
topovec/core/property.py
topovec/core/system.py
topovec/cuda/__init__.py
topovec/io/__init__.py
topovec/marimo/__init__.py
topovec/matplotlib/__init__.py
topovec/matplotlib/layer.py
topovec/mgl/__init__.py
topovec/mgl/axes.py
topovec/mgl/buffer.py
topovec/mgl/camera.py
topovec/mgl/charge.py
topovec/mgl/elements.py
topovec/mgl/flow.py
topovec/mgl/image.py
topovec/mgl/isolines.py
topovec/mgl/level.py
topovec/mgl/render.py
topovec/mgl/scene.py
topovec/mgl/solid.py
topovec/mgl/sphere.py
topovec/mgl/sugar.py
topovec/mgl/vector.py
topovec/sad/__init__.py
topovec/sad/io.py
topovec/ti/__init__.py
topovec/ti/optics.py
topovec-0.1.3.dist-info/METADATA
topovec-0.1.3.dist-info/WHEEL
topovec-0.1.3.dist-info/entry_points.txt
topovec-0.1.3.dist-info/licenses/LICENSE.md
topovec-0.1.3.dist-info/RECORD
