Metadata-Version: 2.4
Name: topovec
Version: 0.1.3
Summary: Visualizer of 3d vector field with accent of topological solitons.
Project-URL: Repository, https://gitlab.com/alepoydes/topovec
Project-URL: Issues, https://gitlab.com/alepoydes/topovec/-/issues
Author-email: Igor Lobanov <lobanov.igor@gmail.com>
License-Expression: MIT
License-File: LICENSE.md
Keywords: liquid crystal,magnetization,physics,soliton,topology,visualization
Classifier: Development Status :: 3 - Alpha
Classifier: Intended Audience :: Science/Research
Classifier: License :: OSI Approved :: MIT License
Classifier: Topic :: Scientific/Engineering :: Physics
Classifier: Topic :: Scientific/Engineering :: Visualization
Requires-Python: >=3.10
Requires-Dist: numpy>=2.1
Requires-Dist: pillow>=11.1.0
Requires-Dist: rich>=13.9.4
Requires-Dist: scipy>=1.15.2
Provides-Extra: cuda
Requires-Dist: numba>=0.61; extra == 'cuda'
Provides-Extra: marimo
Requires-Dist: marimo; extra == 'marimo'
Provides-Extra: matplotlib
Requires-Dist: matplotlib>=3.10.1; extra == 'matplotlib'
Provides-Extra: mgl
Requires-Dist: moderngl>=5.12.0; extra == 'mgl'
Provides-Extra: sad
Requires-Dist: sadcompressor>=0.0.2; extra == 'sad'
Provides-Extra: ti
Requires-Dist: taichi>=1.7.3; extra == 'ti'
